reahl_bzrsupport-3.2.0-py3.4-nspkg.pth
setup.py
reahl/bzrsupport.py
reahl/bzrsupport_dev/__init__.py
reahl/bzrsupport_dev/bzrtests.py
reahl_bzrsupport-3.2.0.dist-info/top_level.txt
reahl_bzrsupport-3.2.0.dist-info/WHEEL
reahl_bzrsupport-3.2.0.dist-info/RECORD
reahl_bzrsupport-3.2.0.dist-info/entry_points.txt
reahl_bzrsupport-3.2.0.dist-info/metadata.json
reahl_bzrsupport-3.2.0.dist-info/METADATA
reahl_bzrsupport-3.2.0.dist-info/DESCRIPTION.rst
reahl_bzrsupport-3.2.0.dist-info/namespace_packages.txt
