Metadata-Version: 2.0
Name: reahl-bzrsupport
Version: 3.2.0
Summary: Distutils support for Bazaar when using Reahl development tools.
Home-page: http://www.reahl.org
Author: Iwan Vosloo
Author-email: iwan@reahl.org
License: UNKNOWN
Platform: UNKNOWN
